diffusion_sde/__init__.py
diffusion_sde/datasets.py
diffusion_sde/diffSDE.py
diffusion_sde/version.py
diffusion_sde/configs/__init__.py
diffusion_sde/configs/config.py
diffusion_sde/models/__init__.py
diffusion_sde/models/ema.py
diffusion_sde/models/nn.py
diffusion_sde/models/unet.py
diffusion_sde/models/utils.py
diffusion_sde/ops/__init__.py
diffusion_sde/ops/loss.py
diffusion_sde/ops/preprocess.py
diffusion_sde/ops/sampling.py
diffusion_sde/ops/sde.py
diffusion_sde-0.1.1.dist-info/LICENSE
diffusion_sde-0.1.1.dist-info/METADATA
diffusion_sde-0.1.1.dist-info/WHEEL
diffusion_sde-0.1.1.dist-info/top_level.txt
diffusion_sde-0.1.1.dist-info/RECORD
