Metadata-Version: 2.1
Name: diffusion-sde
Version: 0.1.1
Summary: Use score-based generative models to generate new images.
Home-page: https://github.com/Ishan-phys/Diffusion-SDE.git
Author: Ishan Srivastava
Author-email: ishan.alld@gmail.com
License: MIT
Keywords: generative modelling,SDE,diffusion models
Platform: UNKNOWN
Classifier: Development Status :: 3 - Alpha
Classifier: Topic :: Software Development :: Build Tools
Classifier: License :: OSI Approved :: MIT License
Classifier: Environment :: Console
Classifier: Operating System :: OS Independent
Classifier: Intended Audience :: Science/Research
Classifier: Intended Audience :: Developers
Classifier: Topic :: Scientific/Engineering
Classifier: Programming Language :: Python :: 3
Classifier: Programming Language :: Python :: 3.7
Classifier: Programming Language :: Python :: 3.8
Classifier: Programming Language :: Python :: 3.9
Classifier: Programming Language :: Python :: 3.10
Requires-Python: >=3.7
License-File: LICENSE
Requires-Dist: matplotlib (>=3.2.0)
Requires-Dist: numpy (>=1.16.0)
Requires-Dist: Pillow (>=8.4.0)
Requires-Dist: torch (>=1.10.2)
Requires-Dist: torchvision (>=0.11.3)
Requires-Dist: tqdm (>=4.59.0)
